setup.cfg
setup.py
pyflagr/Comparator.py
pyflagr/Kemeny.py
pyflagr/Linear.py
pyflagr/Majoritarian.py
pyflagr/MarkovChains.py
pyflagr/RAM.py
pyflagr/RRA.py
pyflagr/Weighted.py
pyflagr/__init__.py
pyflagr/flagr.dll
pyflagr/flagr.dylib
pyflagr/flagr.so
pyflagr/libgcc_s_seh-1.dll
pyflagr/libstdc++-6.dll
pyflagr/test_local.py
pyflagr.egg-info/PKG-INFO
pyflagr.egg-info/SOURCES.txt
pyflagr.egg-info/dependency_links.txt
pyflagr.egg-info/requires.txt
pyflagr.egg-info/top_level.txt