Metadata-Version: 2.1
Name: pyflagr
Version: 1.0.14
Summary: PyFLAGR is a Python package for aggregating ranked preference lists from multiple sources.
Home-page: https://github.com/lakritidis/FLAGR
Author: Leonidas Akritidis
Author-email: lakritidis@ihu.gr
Maintainer: Leonidas Akritidis
Maintainer-email: lakritidis@ihu.gr
License: Apache
Keywords: rank aggregation,rank fusion,data fusion,unsupervised learning,information retrieval,metasearch,metasearch engines,borda count,condorcet,kendall,spearman
Requires-Dist: pandas
Requires-Dist: matplotlib
